ccfreeze/__init__.py
ccfreeze/__main__.py
ccfreeze/bdist_bbfreeze.py
ccfreeze/codehack.py
ccfreeze/eggutil.py
ccfreeze/ensure_setuptools.py
ccfreeze/freezer.py
ccfreeze/getdeps.py
ccfreeze/load_console.py
ccfreeze/py.py
ccfreeze/recipes.py
ccfreeze/winexeutil.py
ccfreeze/modulegraph/__init__.py
ccfreeze/modulegraph/__main__.py
ccfreeze/modulegraph/_compat.py
ccfreeze/modulegraph/find_modules.py
ccfreeze/modulegraph/modulegraph.py
ccfreeze/modulegraph/util.py
ccfreeze/modulegraph/zipio.py
ccfreeze-1.1.5.dist-info/DESCRIPTION.rst
ccfreeze-1.1.5.dist-info/METADATA
ccfreeze-1.1.5.dist-info/RECORD
ccfreeze-1.1.5.dist-info/WHEEL
ccfreeze-1.1.5.dist-info/entry_points.txt
ccfreeze-1.1.5.dist-info/metadata.json
ccfreeze-1.1.5.dist-info/top_level.txt
