Metadata-Version: 2.0
Name: ccfreeze
Version: 1.1.5
Summary: create standalone executables from python scripts
Home-page: https://pypi.python.org/pypi/ccfreeze/
Author: Josh Brown
Author-email: cars1189@aol.com
License: zlib/libpng license
Platform: Linux Windows
Classifier: Development Status :: 5 - Production/Stable
Classifier: License :: OSI Approved :: zlib/libpng License
Classifier: Intended Audience :: Developers
Classifier: Programming Language :: Python
Classifier: Programming Language :: Python :: 2
Classifier: Programming Language :: Python :: 2.7
Classifier: Topic :: Software Development :: Build Tools
Classifier: Topic :: System :: Software Distribution
Requires-Dist: altgraph (>=0.12)
Requires-Dist: ccfreeze-loader (>=1.1.0)
Requires-Dist: pefile
